simplescraper/__init__.py
simplescraper/scraper.py
simplescraper-0.1.3.dist-info/DESCRIPTION.rst
simplescraper-0.1.3.dist-info/METADATA
simplescraper-0.1.3.dist-info/RECORD
simplescraper-0.1.3.dist-info/WHEEL
simplescraper-0.1.3.dist-info/metadata.json
simplescraper-0.1.3.dist-info/top_level.txt
