Metadata-Version: 2.0
Name: simplescraper
Version: 0.1.3
Summary: A simple python web scraper
Home-page: https://github.com/ROZ32/pythonScraper
Author: Oscar Sanchez
Author-email: hmax.bf4@gmail.com
License: MIT License
Platform: any
Classifier: Programming Language :: Python
Classifier: Development Status :: 4 - Beta
Classifier: Natural Language :: English
Classifier: Environment :: Web Environment
Classifier: Intended Audience :: Developers
Classifier: License :: OSI Approved :: MIT License
Classifier: Operating System :: OS Independent
Requires-Dist: beautifulsoup4
Requires-Dist: html5lib
Provides-Extra: testing
Requires-Dist: mock; extra == 'testing'
Requires-Dist: pytest; extra == 'testing'
